verifastscore/__init__.py
verifastscore/search_API.py
verifastscore/verifastscore.py
verifastscore/prompts/PromptCausalLM.py
verifastscore/prompts/__init__.py
verifastscore-0.1.5.dist-info/METADATA
verifastscore-0.1.5.dist-info/WHEEL
verifastscore-0.1.5.dist-info/entry_points.txt
verifastscore-0.1.5.dist-info/top_level.txt
verifastscore-0.1.5.dist-info/RECORD
