Metadata-Version: 2.4
Name: verifastscore
Version: 0.1.5
Summary: Fast, end-to-end factuality evaluation for long-form LLM responses.
Home-page: https://github.com/rishanthrajendhran/verifastscore
Author: Rishanth Rajendhran
Author-email: rishanth@umd.edu
License: Apache 2.0
Requires-Python: >=3.9
Requires-Dist: torch
Requires-Dist: transformers
Requires-Dist: spacy
Requires-Dist: tqdm
Requires-Dist: regex
Requires-Dist: requests
Dynamic: author
Dynamic: author-email
Dynamic: description
Dynamic: description-content-type
Dynamic: home-page
Dynamic: license
Dynamic: requires-dist
Dynamic: requires-python
Dynamic: summary
